<Properties StartupConfiguration="{A25485E7-7201-4D45-A700-973EE493EEF7}|Default">
  <MonoDevelop.Ide.ItemProperties.RESTFUL.api PreferredExecutionTarget="MonoDevelop.Default" />
  <MonoDevelop.Ide.Workbench ActiveDocument="Startup.cs">
    <Files>
      <File FileName="9ccfc4c1-0ee0-4-231-b9ee.publishsettings.xml" Line="11" Column="15" />
      <File FileName=".publishsettings" Line="1" Column="1" />
      <File FileName="appsettings.Development.json" Line="1" Column="1" />
      <File FileName="appsettings.json" Line="1" Column="1" />
      <File FileName="Startup.cs" Line="1" Column="1" />
    </Files>
    <Pads>
      <Pad Id="ProjectPad">
        <State name="__root__">
          <Node name="RESTFUL.api" expanded="True">
            <Node name="RESTFUL.api" expanded="True" selected="True">
              <Node name="Controllers" expanded="True" />
            </Node>
          </Node>
        </State>
      </Pad>
    </Pads>
  </MonoDevelop.Ide.Workbench>
  <MonoDevelop.Ide.DebuggingService.PinnedWatches />
  <MonoDevelop.Ide.Workspace ActiveConfiguration="Debug" />
  <MonoDevelop.Ide.DebuggingService.Breakpoints>
    <BreakpointStore />
  </MonoDevelop.Ide.DebuggingService.Breakpoints>
  <MultiItemStartupConfigurations />
  <AuthorInfo Name="cliffordcrerar" Email="cliff.crerar@gmail.com" Copyright="" Company="" Trademark="" />
</Properties>